correios_sigep/__init__.py
correios_sigep/client.py
correios_sigep/models/__init__.py
correios_sigep/models/additional_service.py
correios_sigep/models/correios_log.py
correios_sigep/models/national.py
correios_sigep/models/object_dimension.py
correios_sigep/models/plp.py
correios_sigep/models/postal_object.py
correios_sigep/models/recipient.py
correios_sigep/models/sender.py
correios_sigep/models/tag.py
correios_sigep/reports/__init__.py
correios_sigep/reports/generator.py
correios_sigep/reports/plp.py
correios_sigep/reports/tag.py
correios_sigep/utils/__init__.py
correios_sigep/utils/dict.py
correios_sigep/utils/etree.py
correios_sigep/utils/number.py
correios_sigep/utils/validators.py
correios_sigep-0.1.1.dist-info/METADATA
correios_sigep-0.1.1.dist-info/WHEEL
correios_sigep-0.1.1.dist-info/top_level.txt
correios_sigep-0.1.1.dist-info/RECORD
