Metadata-Version: 2.1
Name: correios-sigep
Version: 0.1.1
Summary: correios sigep
Home-page: https://github.com/brunocasado/correios-sigep
Author: Bruno Casado
Author-email: contato@brunocasado.me
License: MIT
Platform: UNKNOWN
Requires-Dist: lxml
Requires-Dist: zeep
Requires-Dist: elaphe
Requires-Dist: qrcode
Requires-Dist: pdfkit
Requires-Dist: candybar
Requires-Dist: huBarcode
